{
  "route": "CDG-NRT",
  "origin": "CDG",
  "dest": "NRT",
  "label": "Paris (CDG) \u2192  Tokyo (NRT)",
  "prices": [
    {
      "date": "2024-07-05",
      "price": 12500,
      "airline": "Various"
    },
    {
      "date": "2024-07-06",
      "price": 12450,
      "airline": "ANA"
    },
    {
      "date": "2024-07-07",
      "price": 11000,
      "airline": "Various"
    },
    {
      "date": "2024-07-08",
      "price": 11690,
      "airline": "Japan Airlines"
    },
    {
      "date": "2024-07-09",
      "price": 11400,
      "airline": "Japan Airlines"
    },
    {
      "date": "2024-07-10",
      "price": 9460,
      "airline": "Air France"
    },
    {
      "date": "2024-07-11",
      "price": 9420,
      "airline": "Air France"
    },
    {
      "date": "2024-07-12",
      "price": 12720,
      "airline": "Various"
    },
    {
      "date": "2024-07-13",
      "price": 11790,
      "airline": "Various"
    },
    {
      "date": "2024-07-14",
      "price": 12810,
      "airline": "ANA"
    },
    {
      "date": "2024-07-15",
      "price": 10380,
      "airline": "ANA"
    },
    {
      "date": "2024-07-16",
      "price": 11590,
      "airline": "ANA"
    },
    {
      "date": "2024-07-17",
      "price": 10980,
      "airline": "Air France"
    },
    {
      "date": "2024-07-18",
      "price": 10800,
      "airline": "Various"
    },
    {
      "date": "2024-07-19",
      "price": 11890,
      "airline": "Various"
    },
    {
      "date": "2024-07-20",
      "price": 12550,
      "airline": "Air France"
    },
    {
      "date": "2024-07-21",
      "price": 11290,
      "airline": "ANA"
    },
    {
      "date": "2024-07-22",
      "price": 10260,
      "airline": "Air France"
    },
    {
      "date": "2024-07-23",
      "price": 11590,
      "airline": "Various"
    },
    {
      "date": "2024-07-24",
      "price": 9910,
      "airline": "Air France"
    },
    {
      "date": "2024-07-25",
      "price": 9750,
      "airline": "Various"
    },
    {
      "date": "2024-07-26",
      "price": 11730,
      "airline": "Various"
    },
    {
      "date": "2024-07-27",
      "price": 9820,
      "airline": "ANA"
    },
    {
      "date": "2024-07-28",
      "price": 11300,
      "airline": "Japan Airlines"
    },
    {
      "date": "2024-07-29",
      "price": 12980,
      "airline": "Various"
    },
    {
      "date": "2024-07-30",
      "price": 11680,
      "airline": "ANA"
    },
    {
      "date": "2024-07-31",
      "price": 10200,
      "airline": "Various"
    },
    {
      "date": "2024-08-01",
      "price": 10680,
      "airline": "Air France"
    },
    {
      "date": "2024-08-02",
      "price": 12240,
      "airline": "Japan Airlines"
    },
    {
      "date": "2024-08-03",
      "price": 11150,
      "airline": "Air France"
    },
    {
      "date": "2024-08-04",
      "price": 10510,
      "airline": "Japan Airlines"
    },
    {
      "date": "2024-08-05",
      "price": 10850,
      "airline": "ANA"
    },
    {
      "date": "2024-08-06",
      "price": 10030,
      "airline": "Various"
    },
    {
      "date": "2024-08-07",
      "price": 9960,
      "airline": "Various"
    },
    {
      "date": "2024-08-08",
      "price": 10050,
      "airline": "Japan Airlines"
    },
    {
      "date": "2024-08-09",
      "price": 9980,
      "airline": "Various"
    },
    {
      "date": "2024-08-10",
      "price": 11140,
      "airline": "Various"
    },
    {
      "date": "2024-08-11",
      "price": 10430,
      "airline": "ANA"
    },
    {
      "date": "2024-08-12",
      "price": 9550,
      "airline": "Air France"
    },
    {
      "date": "2024-08-13",
      "price": 10770,
      "airline": "Air France"
    },
    {
      "date": "2024-08-14",
      "price": 10910,
      "airline": "Air France"
    },
    {
      "date": "2024-08-15",
      "price": 10790,
      "airline": "ANA"
    },
    {
      "date": "2024-08-16",
      "price": 12270,
      "airline": "Air France"
    },
    {
      "date": "2024-08-17",
      "price": 12630,
      "airline": "Various"
    },
    {
      "date": "2024-08-18",
      "price": 11350,
      "airline": "Various"
    },
    {
      "date": "2024-08-19",
      "price": 10420,
      "airline": "ANA"
    },
    {
      "date": "2024-08-20",
      "price": 11470,
      "airline": "Japan Airlines"
    },
    {
      "date": "2024-08-21",
      "price": 9890,
      "airline": "Japan Airlines"
    },
    {
      "date": "2024-08-22",
      "price": 9800,
      "airline": "Air France"
    },
    {
      "date": "2024-08-23",
      "price": 11390,
      "airline": "Air France"
    },
    {
      "date": "2024-08-24",
      "price": 11710,
      "airline": "Various"
    },
    {
      "date": "2024-08-25",
      "price": 12940,
      "airline": "Japan Airlines"
    },
    {
      "date": "2024-08-26",
      "price": 10060,
      "airline": "ANA"
    },
    {
      "date": "2024-08-27",
      "price": 10050,
      "airline": "Japan Airlines"
    },
    {
      "date": "2024-08-28",
      "price": 10880,
      "airline": "Japan Airlines"
    },
    {
      "date": "2024-08-29",
      "price": 10770,
      "airline": "ANA"
    },
    {
      "date": "2024-08-30",
      "price": 12190,
      "airline": "ANA"
    },
    {
      "date": "2024-08-31",
      "price": 10630,
      "airline": "Air France"
    },
    {
      "date": "2024-09-01",
      "price": 11990,
      "airline": "Japan Airlines"
    },
    {
      "date": "2024-09-02",
      "price": 10280,
      "airline": "Japan Airlines"
    },
    {
      "date": "2024-09-03",
      "price": 10320,
      "airline": "Air France"
    },
    {
      "date": "2024-09-04",
      "price": 9330,
      "airline": "ANA"
    },
    {
      "date": "2024-09-05",
      "price": 10630,
      "airline": "Japan Airlines"
    },
    {
      "date": "2024-09-06",
      "price": 10660,
      "airline": "Japan Airlines"
    },
    {
      "date": "2024-09-07",
      "price": 10870,
      "airline": "Various"
    },
    {
      "date": "2024-09-08",
      "price": 12820,
      "airline": "ANA"
    },
    {
      "date": "2024-09-09",
      "price": 12400,
      "airline": "Japan Airlines"
    },
    {
      "date": "2024-09-10",
      "price": 10780,
      "airline": "Air France"
    },
    {
      "date": "2024-09-11",
      "price": 10020,
      "airline": "Various"
    },
    {
      "date": "2024-09-12",
      "price": 10070,
      "airline": "ANA"
    },
    {
      "date": "2024-09-13",
      "price": 12100,
      "airline": "Various"
    },
    {
      "date": "2024-09-14",
      "price": 10140,
      "airline": "ANA"
    },
    {
      "date": "2024-09-15",
      "price": 11980,
      "airline": "ANA"
    },
    {
      "date": "2024-09-16",
      "price": 10110,
      "airline": "Air France"
    },
    {
      "date": "2024-09-17",
      "price": 10770,
      "airline": "Air France"
    },
    {
      "date": "2024-09-18",
      "price": 8850,
      "airline": "Air France"
    },
    {
      "date": "2024-09-19",
      "price": 11410,
      "airline": "Various"
    },
    {
      "date": "2024-09-20",
      "price": 10580,
      "airline": "ANA"
    },
    {
      "date": "2024-09-21",
      "price": 10810,
      "airline": "Japan Airlines"
    },
    {
      "date": "2024-09-22",
      "price": 12450,
      "airline": "Japan Airlines"
    },
    {
      "date": "2024-09-23",
      "price": 10100,
      "airline": "Air France"
    },
    {
      "date": "2024-09-24",
      "price": 10010,
      "airline": "ANA"
    },
    {
      "date": "2024-09-25",
      "price": 11070,
      "airline": "ANA"
    },
    {
      "date": "2024-09-26",
      "price": 10810,
      "airline": "Japan Airlines"
    },
    {
      "date": "2024-09-27",
      "price": 11460,
      "airline": "ANA"
    },
    {
      "date": "2024-09-28",
      "price": 12780,
      "airline": "Various"
    },
    {
      "date": "2024-09-29",
      "price": 12140,
      "airline": "Japan Airlines"
    },
    {
      "date": "2024-09-30",
      "price": 10100,
      "airline": "Air France"
    },
    {
      "date": "2024-10-01",
      "price": 11220,
      "airline": "Japan Airlines"
    },
    {
      "date": "2024-10-02",
      "price": 10490,
      "airline": "Japan Airlines"
    },
    {
      "date": "2024-10-03",
      "price": 8830,
      "airline": "Various"
    },
    {
      "date": "2024-10-04",
      "price": 11200,
      "airline": "Air France"
    },
    {
      "date": "2024-10-05",
      "price": 11170,
      "airline": "Air France"
    },
    {
      "date": "2024-10-06",
      "price": 11670,
      "airline": "Japan Airlines"
    },
    {
      "date": "2024-10-07",
      "price": 9990,
      "airline": "Various"
    },
    {
      "date": "2024-10-08",
      "price": 9740,
      "airline": "Various"
    },
    {
      "date": "2024-10-09",
      "price": 9260,
      "airline": "Japan Airlines"
    },
    {
      "date": "2024-10-10",
      "price": 10570,
      "airline": "Air France"
    },
    {
      "date": "2024-10-11",
      "price": 11580,
      "airline": "ANA"
    },
    {
      "date": "2024-10-12",
      "price": 12170,
      "airline": "Air France"
    },
    {
      "date": "2024-10-13",
      "price": 11310,
      "airline": "Japan Airlines"
    },
    {
      "date": "2024-10-14",
      "price": 10900,
      "airline": "Air France"
    },
    {
      "date": "2024-10-15",
      "price": 11580,
      "airline": "Various"
    },
    {
      "date": "2024-10-16",
      "price": 11920,
      "airline": "Japan Airlines"
    },
    {
      "date": "2024-10-17",
      "price": 9470,
      "airline": "ANA"
    },
    {
      "date": "2024-10-18",
      "price": 12110,
      "airline": "ANA"
    },
    {
      "date": "2024-10-19",
      "price": 12580,
      "airline": "Japan Airlines"
    },
    {
      "date": "2024-10-20",
      "price": 11140,
      "airline": "Japan Airlines"
    },
    {
      "date": "2024-10-21",
      "price": 12070,
      "airline": "ANA"
    },
    {
      "date": "2024-10-22",
      "price": 11290,
      "airline": "Japan Airlines"
    },
    {
      "date": "2024-10-23",
      "price": 12160,
      "airline": "Various"
    },
    {
      "date": "2024-10-24",
      "price": 10610,
      "airline": "Various"
    },
    {
      "date": "2024-10-25",
      "price": 11890,
      "airline": "ANA"
    },
    {
      "date": "2024-10-26",
      "price": 10780,
      "airline": "ANA"
    },
    {
      "date": "2024-10-27",
      "price": 10190,
      "airline": "Japan Airlines"
    },
    {
      "date": "2024-10-28",
      "price": 11310,
      "airline": "Japan Airlines"
    },
    {
      "date": "2024-10-29",
      "price": 11410,
      "airline": "Various"
    },
    {
      "date": "2024-10-30",
      "price": 9980,
      "airline": "Air France"
    },
    {
      "date": "2024-10-31",
      "price": 10680,
      "airline": "Various"
    },
    {
      "date": "2024-11-01",
      "price": 13850,
      "airline": "Various"
    },
    {
      "date": "2024-11-02",
      "price": 12590,
      "airline": "Air France"
    },
    {
      "date": "2024-11-03",
      "price": 12140,
      "airline": "Various"
    },
    {
      "date": "2024-11-04",
      "price": 11380,
      "airline": "Various"
    },
    {
      "date": "2024-11-05",
      "price": 13310,
      "airline": "Japan Airlines"
    },
    {
      "date": "2024-11-06",
      "price": 11830,
      "airline": "ANA"
    },
    {
      "date": "2024-11-07",
      "price": 11110,
      "airline": "Various"
    },
    {
      "date": "2024-11-08",
      "price": 12110,
      "airline": "Air France"
    },
    {
      "date": "2024-11-09",
      "price": 15800,
      "airline": "ANA"
    },
    {
      "date": "2024-11-10",
      "price": 12730,
      "airline": "Japan Airlines"
    },
    {
      "date": "2024-11-11",
      "price": 10720,
      "airline": "Various"
    },
    {
      "date": "2024-11-12",
      "price": 12540,
      "airline": "Japan Airlines"
    },
    {
      "date": "2024-11-13",
      "price": 12490,
      "airline": "Japan Airlines"
    },
    {
      "date": "2024-11-14",
      "price": 11520,
      "airline": "Various"
    },
    {
      "date": "2024-11-15",
      "price": 14430,
      "airline": "Various"
    },
    {
      "date": "2024-11-16",
      "price": 13320,
      "airline": "Air France"
    },
    {
      "date": "2024-11-17",
      "price": 13770,
      "airline": "Air France"
    },
    {
      "date": "2024-11-18",
      "price": 11730,
      "airline": "Air France"
    },
    {
      "date": "2024-11-19",
      "price": 12640,
      "airline": "Air France"
    },
    {
      "date": "2024-11-20",
      "price": 9870,
      "airline": "Japan Airlines"
    },
    {
      "date": "2024-11-21",
      "price": 8900,
      "airline": "Japan Airlines"
    },
    {
      "date": "2024-11-22",
      "price": 14340,
      "airline": "Various"
    },
    {
      "date": "2024-11-23",
      "price": 12530,
      "airline": "Various"
    },
    {
      "date": "2024-11-24",
      "price": 12870,
      "airline": "Japan Airlines"
    },
    {
      "date": "2024-11-25",
      "price": 10150,
      "airline": "Japan Airlines"
    },
    {
      "date": "2024-11-26",
      "price": 12980,
      "airline": "Japan Airlines"
    },
    {
      "date": "2024-11-27",
      "price": 11870,
      "airline": "Air France"
    },
    {
      "date": "2024-11-28",
      "price": 10610,
      "airline": "Air France"
    },
    {
      "date": "2024-11-29",
      "price": 13210,
      "airline": "Various"
    },
    {
      "date": "2024-11-30",
      "price": 12930,
      "airline": "ANA"
    },
    {
      "date": "2024-12-01",
      "price": 13270,
      "airline": "Air France"
    },
    {
      "date": "2024-12-02",
      "price": 12120,
      "airline": "Air France"
    },
    {
      "date": "2024-12-03",
      "price": 13030,
      "airline": "Various"
    },
    {
      "date": "2024-12-04",
      "price": 11990,
      "airline": "Various"
    },
    {
      "date": "2024-12-05",
      "price": 10650,
      "airline": "Japan Airlines"
    },
    {
      "date": "2024-12-06",
      "price": 13750,
      "airline": "Various"
    },
    {
      "date": "2024-12-07",
      "price": 11950,
      "airline": "Japan Airlines"
    },
    {
      "date": "2024-12-08",
      "price": 14020,
      "airline": "Various"
    },
    {
      "date": "2024-12-09",
      "price": 12020,
      "airline": "ANA"
    },
    {
      "date": "2024-12-10",
      "price": 10070,
      "airline": "Japan Airlines"
    },
    {
      "date": "2024-12-11",
      "price": 11260,
      "airline": "Air France"
    },
    {
      "date": "2024-12-12",
      "price": 12170,
      "airline": "Various"
    },
    {
      "date": "2024-12-13",
      "price": 14560,
      "airline": "Air France"
    },
    {
      "date": "2024-12-14",
      "price": 13300,
      "airline": "ANA"
    },
    {
      "date": "2024-12-15",
      "price": 13300,
      "airline": "Various"
    },
    {
      "date": "2024-12-16",
      "price": 12390,
      "airline": "Japan Airlines"
    },
    {
      "date": "2024-12-17",
      "price": 12110,
      "airline": "Various"
    },
    {
      "date": "2024-12-18",
      "price": 11450,
      "airline": "Japan Airlines"
    },
    {
      "date": "2024-12-19",
      "price": 10810,
      "airline": "Air France"
    },
    {
      "date": "2024-12-20",
      "price": 11670,
      "airline": "Japan Airlines"
    },
    {
      "date": "2024-12-21",
      "price": 14190,
      "airline": "Japan Airlines"
    },
    {
      "date": "2024-12-22",
      "price": 12990,
      "airline": "ANA"
    },
    {
      "date": "2024-12-23",
      "price": 12950,
      "airline": "Various"
    },
    {
      "date": "2024-12-24",
      "price": 10610,
      "airline": "ANA"
    },
    {
      "date": "2024-12-25",
      "price": 12390,
      "airline": "ANA"
    },
    {
      "date": "2024-12-26",
      "price": 10130,
      "airline": "Air France"
    },
    {
      "date": "2024-12-27",
      "price": 14870,
      "airline": "Air France"
    },
    {
      "date": "2024-12-28",
      "price": 12770,
      "airline": "Japan Airlines"
    },
    {
      "date": "2024-12-29",
      "price": 13700,
      "airline": "Japan Airlines"
    },
    {
      "date": "2024-12-30",
      "price": 12590,
      "airline": "Air France"
    },
    {
      "date": "2024-12-31",
      "price": 11870,
      "airline": "Air France"
    },
    {
      "date": "2025-01-01",
      "price": 10720,
      "airline": "Air France"
    },
    {
      "date": "2025-01-02",
      "price": 10110,
      "airline": "Air France"
    },
    {
      "date": "2025-01-03",
      "price": 11740,
      "airline": "ANA"
    },
    {
      "date": "2025-01-04",
      "price": 9840,
      "airline": "Air France"
    },
    {
      "date": "2025-01-05",
      "price": 12300,
      "airline": "Various"
    },
    {
      "date": "2025-01-06",
      "price": 9900,
      "airline": "Air France"
    },
    {
      "date": "2025-01-07",
      "price": 10190,
      "airline": "Japan Airlines"
    },
    {
      "date": "2025-01-08",
      "price": 9890,
      "airline": "Japan Airlines"
    },
    {
      "date": "2025-01-09",
      "price": 9580,
      "airline": "Japan Airlines"
    },
    {
      "date": "2025-01-10",
      "price": 10470,
      "airline": "Air France"
    },
    {
      "date": "2025-01-11",
      "price": 10670,
      "airline": "Various"
    },
    {
      "date": "2025-01-12",
      "price": 11340,
      "airline": "Japan Airlines"
    },
    {
      "date": "2025-01-13",
      "price": 10610,
      "airline": "Air France"
    },
    {
      "date": "2025-01-14",
      "price": 9860,
      "airline": "Japan Airlines"
    },
    {
      "date": "2025-01-15",
      "price": 10290,
      "airline": "Air France"
    },
    {
      "date": "2025-01-16",
      "price": 10810,
      "airline": "ANA"
    },
    {
      "date": "2025-01-17",
      "price": 11150,
      "airline": "Air France"
    },
    {
      "date": "2025-01-18",
      "price": 10010,
      "airline": "Various"
    },
    {
      "date": "2025-01-19",
      "price": 11420,
      "airline": "Japan Airlines"
    },
    {
      "date": "2025-01-20",
      "price": 9460,
      "airline": "ANA"
    },
    {
      "date": "2025-01-21",
      "price": 10810,
      "airline": "Various"
    },
    {
      "date": "2025-01-22",
      "price": 10660,
      "airline": "Japan Airlines"
    },
    {
      "date": "2025-01-23",
      "price": 9580,
      "airline": "Japan Airlines"
    },
    {
      "date": "2025-01-24",
      "price": 10590,
      "airline": "ANA"
    },
    {
      "date": "2025-01-25",
      "price": 11310,
      "airline": "Japan Airlines"
    },
    {
      "date": "2025-01-26",
      "price": 13620,
      "airline": "ANA"
    },
    {
      "date": "2025-01-27",
      "price": 10330,
      "airline": "ANA"
    },
    {
      "date": "2025-01-28",
      "price": 11950,
      "airline": "Air France"
    },
    {
      "date": "2025-01-29",
      "price": 10610,
      "airline": "Japan Airlines"
    },
    {
      "date": "2025-01-30",
      "price": 11180,
      "airline": "Japan Airlines"
    },
    {
      "date": "2025-01-31",
      "price": 11870,
      "airline": "Various"
    },
    {
      "date": "2025-02-01",
      "price": 10820,
      "airline": "Air France"
    },
    {
      "date": "2025-02-02",
      "price": 11080,
      "airline": "ANA"
    },
    {
      "date": "2025-02-03",
      "price": 11400,
      "airline": "ANA"
    },
    {
      "date": "2025-02-04",
      "price": 9280,
      "airline": "Japan Airlines"
    },
    {
      "date": "2025-02-05",
      "price": 10040,
      "airline": "Air France"
    },
    {
      "date": "2025-02-06",
      "price": 10640,
      "airline": "Air France"
    },
    {
      "date": "2025-02-07",
      "price": 12010,
      "airline": "Air France"
    },
    {
      "date": "2025-02-08",
      "price": 10770,
      "airline": "Various"
    },
    {
      "date": "2025-02-09",
      "price": 12090,
      "airline": "ANA"
    },
    {
      "date": "2025-02-10",
      "price": 10550,
      "airline": "Various"
    },
    {
      "date": "2025-02-11",
      "price": 10510,
      "airline": "Air France"
    },
    {
      "date": "2025-02-12",
      "price": 9640,
      "airline": "ANA"
    },
    {
      "date": "2025-02-13",
      "price": 9660,
      "airline": "Various"
    },
    {
      "date": "2025-02-14",
      "price": 11850,
      "airline": "Air France"
    },
    {
      "date": "2025-02-15",
      "price": 10290,
      "airline": "ANA"
    },
    {
      "date": "2025-02-16",
      "price": 10980,
      "airline": "ANA"
    },
    {
      "date": "2025-02-17",
      "price": 10060,
      "airline": "Japan Airlines"
    },
    {
      "date": "2025-02-18",
      "price": 9810,
      "airline": "ANA"
    },
    {
      "date": "2025-02-19",
      "price": 9470,
      "airline": "ANA"
    },
    {
      "date": "2025-02-20",
      "price": 10700,
      "airline": "Air France"
    },
    {
      "date": "2025-02-21",
      "price": 12830,
      "airline": "Air France"
    },
    {
      "date": "2025-02-22",
      "price": 10370,
      "airline": "Various"
    },
    {
      "date": "2025-02-23",
      "price": 12710,
      "airline": "ANA"
    },
    {
      "date": "2025-02-24",
      "price": 11330,
      "airline": "Japan Airlines"
    },
    {
      "date": "2025-02-25",
      "price": 11030,
      "airline": "Air France"
    },
    {
      "date": "2025-02-26",
      "price": 9080,
      "airline": "Various"
    },
    {
      "date": "2025-02-27",
      "price": 11420,
      "airline": "Various"
    },
    {
      "date": "2025-02-28",
      "price": 10830,
      "airline": "Japan Airlines"
    },
    {
      "date": "2025-03-01",
      "price": 14910,
      "airline": "Various"
    },
    {
      "date": "2025-03-02",
      "price": 14040,
      "airline": "Air France"
    },
    {
      "date": "2025-03-03",
      "price": 13850,
      "airline": "Air France"
    },
    {
      "date": "2025-03-04",
      "price": 12000,
      "airline": "Various"
    },
    {
      "date": "2025-03-05",
      "price": 15150,
      "airline": "Various"
    },
    {
      "date": "2025-03-06",
      "price": 14710,
      "airline": "ANA"
    },
    {
      "date": "2025-03-07",
      "price": 13460,
      "airline": "Air France"
    },
    {
      "date": "2025-03-08",
      "price": 15060,
      "airline": "Air France"
    },
    {
      "date": "2025-03-09",
      "price": 13700,
      "airline": "Japan Airlines"
    },
    {
      "date": "2025-03-10",
      "price": 12490,
      "airline": "Air France"
    },
    {
      "date": "2025-03-11",
      "price": 14920,
      "airline": "Japan Airlines"
    },
    {
      "date": "2025-03-12",
      "price": 13820,
      "airline": "Air France"
    },
    {
      "date": "2025-03-13",
      "price": 12350,
      "airline": "Air France"
    },
    {
      "date": "2025-03-14",
      "price": 13270,
      "airline": "Various"
    },
    {
      "date": "2025-03-15",
      "price": 14830,
      "airline": "Japan Airlines"
    },
    {
      "date": "2025-03-16",
      "price": 15470,
      "airline": "Japan Airlines"
    },
    {
      "date": "2025-03-17",
      "price": 14670,
      "airline": "Japan Airlines"
    },
    {
      "date": "2025-03-18",
      "price": 14350,
      "airline": "ANA"
    },
    {
      "date": "2025-03-19",
      "price": 14100,
      "airline": "Air France"
    },
    {
      "date": "2025-03-20",
      "price": 12890,
      "airline": "Japan Airlines"
    },
    {
      "date": "2025-03-21",
      "price": 16040,
      "airline": "Air France"
    },
    {
      "date": "2025-03-22",
      "price": 14140,
      "airline": "Various"
    },
    {
      "date": "2025-03-23",
      "price": 14890,
      "airline": "Various"
    },
    {
      "date": "2025-03-24",
      "price": 11850,
      "airline": "ANA"
    },
    {
      "date": "2025-03-25",
      "price": 13340,
      "airline": "Various"
    },
    {
      "date": "2025-03-26",
      "price": 15260,
      "airline": "Japan Airlines"
    },
    {
      "date": "2025-03-27",
      "price": 11990,
      "airline": "Various"
    },
    {
      "date": "2025-03-28",
      "price": 15190,
      "airline": "Japan Airlines"
    },
    {
      "date": "2025-03-29",
      "price": 16930,
      "airline": "Air France"
    },
    {
      "date": "2025-03-30",
      "price": 18880,
      "airline": "ANA"
    },
    {
      "date": "2025-03-31",
      "price": 14070,
      "airline": "Air France"
    },
    {
      "date": "2025-04-01",
      "price": 13810,
      "airline": "Japan Airlines"
    },
    {
      "date": "2025-04-02",
      "price": 14490,
      "airline": "Japan Airlines"
    },
    {
      "date": "2025-04-03",
      "price": 14200,
      "airline": "ANA"
    },
    {
      "date": "2025-04-04",
      "price": 15280,
      "airline": "Various"
    },
    {
      "date": "2025-04-05",
      "price": 13200,
      "airline": "Japan Airlines"
    },
    {
      "date": "2025-04-06",
      "price": 13500,
      "airline": "Air France"
    },
    {
      "date": "2025-04-07",
      "price": 14410,
      "airline": "Various"
    },
    {
      "date": "2025-04-08",
      "price": 11870,
      "airline": "ANA"
    },
    {
      "date": "2025-04-09",
      "price": 12520,
      "airline": "ANA"
    },
    {
      "date": "2025-04-10",
      "price": 14080,
      "airline": "Air France"
    },
    {
      "date": "2025-04-11",
      "price": 15000,
      "airline": "Air France"
    },
    {
      "date": "2025-04-12",
      "price": 17390,
      "airline": "Japan Airlines"
    },
    {
      "date": "2025-04-13",
      "price": 15160,
      "airline": "ANA"
    },
    {
      "date": "2025-04-14",
      "price": 14240,
      "airline": "ANA"
    },
    {
      "date": "2025-04-15",
      "price": 16110,
      "airline": "ANA"
    },
    {
      "date": "2025-04-16",
      "price": 11940,
      "airline": "Japan Airlines"
    },
    {
      "date": "2025-04-17",
      "price": 14280,
      "airline": "Air France"
    },
    {
      "date": "2025-04-18",
      "price": 13460,
      "airline": "ANA"
    },
    {
      "date": "2025-04-19",
      "price": 14700,
      "airline": "Japan Airlines"
    },
    {
      "date": "2025-04-20",
      "price": 14130,
      "airline": "Various"
    },
    {
      "date": "2025-04-21",
      "price": 13610,
      "airline": "Various"
    },
    {
      "date": "2025-04-22",
      "price": 13500,
      "airline": "Various"
    },
    {
      "date": "2025-04-23",
      "price": 15320,
      "airline": "ANA"
    },
    {
      "date": "2025-04-24",
      "price": 14760,
      "airline": "Air France"
    },
    {
      "date": "2025-04-25",
      "price": 15800,
      "airline": "Air France"
    },
    {
      "date": "2025-04-26",
      "price": 16270,
      "airline": "Various"
    },
    {
      "date": "2025-04-27",
      "price": 16200,
      "airline": "Japan Airlines"
    },
    {
      "date": "2025-04-28",
      "price": 12920,
      "airline": "Air France"
    },
    {
      "date": "2025-04-29",
      "price": 14140,
      "airline": "Various"
    },
    {
      "date": "2025-04-30",
      "price": 13990,
      "airline": "Various"
    },
    {
      "date": "2025-05-01",
      "price": 10210,
      "airline": "Various"
    },
    {
      "date": "2025-05-02",
      "price": 11790,
      "airline": "ANA"
    },
    {
      "date": "2025-05-03",
      "price": 10890,
      "airline": "Japan Airlines"
    },
    {
      "date": "2025-05-04",
      "price": 10840,
      "airline": "ANA"
    },
    {
      "date": "2025-05-05",
      "price": 11260,
      "airline": "Japan Airlines"
    },
    {
      "date": "2025-05-06",
      "price": 10540,
      "airline": "ANA"
    },
    {
      "date": "2025-05-07",
      "price": 11430,
      "airline": "Various"
    },
    {
      "date": "2025-05-08",
      "price": 11890,
      "airline": "ANA"
    },
    {
      "date": "2025-05-09",
      "price": 13640,
      "airline": "ANA"
    },
    {
      "date": "2025-05-10",
      "price": 11420,
      "airline": "ANA"
    },
    {
      "date": "2025-05-11",
      "price": 12240,
      "airline": "Air France"
    },
    {
      "date": "2025-05-12",
      "price": 10420,
      "airline": "Japan Airlines"
    },
    {
      "date": "2025-05-13",
      "price": 9410,
      "airline": "Japan Airlines"
    },
    {
      "date": "2025-05-14",
      "price": 10080,
      "airline": "Air France"
    },
    {
      "date": "2025-05-15",
      "price": 11300,
      "airline": "Japan Airlines"
    },
    {
      "date": "2025-05-16",
      "price": 11760,
      "airline": "Air France"
    },
    {
      "date": "2025-05-17",
      "price": 12170,
      "airline": "Air France"
    },
    {
      "date": "2025-05-18",
      "price": 10920,
      "airline": "Various"
    },
    {
      "date": "2025-05-19",
      "price": 10810,
      "airline": "Various"
    },
    {
      "date": "2025-05-20",
      "price": 10450,
      "airline": "Various"
    },
    {
      "date": "2025-05-21",
      "price": 10250,
      "airline": "ANA"
    },
    {
      "date": "2025-05-22",
      "price": 9970,
      "airline": "Japan Airlines"
    },
    {
      "date": "2025-05-23",
      "price": 11040,
      "airline": "ANA"
    },
    {
      "date": "2025-05-24",
      "price": 10950,
      "airline": "Various"
    },
    {
      "date": "2025-05-25",
      "price": 11470,
      "airline": "Japan Airlines"
    },
    {
      "date": "2025-05-26",
      "price": 10480,
      "airline": "Japan Airlines"
    },
    {
      "date": "2025-05-27",
      "price": 9390,
      "airline": "Air France"
    },
    {
      "date": "2025-05-28",
      "price": 10670,
      "airline": "ANA"
    },
    {
      "date": "2025-05-29",
      "price": 8790,
      "airline": "Various"
    },
    {
      "date": "2025-05-30",
      "price": 13090,
      "airline": "ANA"
    },
    {
      "date": "2025-05-31",
      "price": 9880,
      "airline": "Japan Airlines"
    },
    {
      "date": "2025-06-01",
      "price": 11870,
      "airline": "Various"
    },
    {
      "date": "2025-06-02",
      "price": 10530,
      "airline": "ANA"
    },
    {
      "date": "2025-06-03",
      "price": 10700,
      "airline": "ANA"
    },
    {
      "date": "2025-06-04",
      "price": 10090,
      "airline": "ANA"
    },
    {
      "date": "2025-06-05",
      "price": 11640,
      "airline": "Japan Airlines"
    },
    {
      "date": "2025-06-06",
      "price": 11020,
      "airline": "Japan Airlines"
    },
    {
      "date": "2025-06-07",
      "price": 11410,
      "airline": "Air France"
    },
    {
      "date": "2025-06-08",
      "price": 11680,
      "airline": "Various"
    },
    {
      "date": "2025-06-09",
      "price": 10640,
      "airline": "Japan Airlines"
    },
    {
      "date": "2025-06-10",
      "price": 10920,
      "airline": "Air France"
    },
    {
      "date": "2025-06-11",
      "price": 11080,
      "airline": "Various"
    },
    {
      "date": "2025-06-12",
      "price": 10450,
      "airline": "Air France"
    },
    {
      "date": "2025-06-13",
      "price": 12450,
      "airline": "Japan Airlines"
    },
    {
      "date": "2025-06-14",
      "price": 9890,
      "airline": "Japan Airlines"
    },
    {
      "date": "2025-06-15",
      "price": 12930,
      "airline": "Japan Airlines"
    },
    {
      "date": "2025-06-16",
      "price": 9850,
      "airline": "ANA"
    },
    {
      "date": "2025-06-17",
      "price": 10460,
      "airline": "Japan Airlines"
    },
    {
      "date": "2025-06-18",
      "price": 10130,
      "airline": "Japan Airlines"
    },
    {
      "date": "2025-06-19",
      "price": 10710,
      "airline": "Various"
    },
    {
      "date": "2025-06-20",
      "price": 11560,
      "airline": "ANA"
    },
    {
      "date": "2025-06-21",
      "price": 10390,
      "airline": "Air France"
    },
    {
      "date": "2025-06-22",
      "price": 11500,
      "airline": "ANA"
    },
    {
      "date": "2025-06-23",
      "price": 10150,
      "airline": "ANA"
    },
    {
      "date": "2025-06-24",
      "price": 9320,
      "airline": "Japan Airlines"
    },
    {
      "date": "2025-06-25",
      "price": 10730,
      "airline": "Various"
    },
    {
      "date": "2025-06-26",
      "price": 9780,
      "airline": "ANA"
    },
    {
      "date": "2025-06-27",
      "price": 11610,
      "airline": "Japan Airlines"
    },
    {
      "date": "2025-06-28",
      "price": 10480,
      "airline": "Various"
    },
    {
      "date": "2025-06-29",
      "price": 11830,
      "airline": "ANA"
    },
    {
      "date": "2025-06-30",
      "price": 9790,
      "airline": "Various"
    },
    {
      "date": "2025-07-01",
      "price": 10930,
      "airline": "ANA"
    },
    {
      "date": "2025-07-02",
      "price": 10280,
      "airline": "ANA"
    },
    {
      "date": "2025-07-03",
      "price": 12660,
      "airline": "ANA"
    },
    {
      "date": "2025-07-04",
      "price": 11730,
      "airline": "Various"
    },
    {
      "date": "2025-07-05",
      "price": 11780,
      "airline": "Various"
    },
    {
      "date": "2025-07-06",
      "price": 9820,
      "airline": "ANA"
    },
    {
      "date": "2025-07-07",
      "price": 9410,
      "airline": "Japan Airlines"
    },
    {
      "date": "2025-07-08",
      "price": 9820,
      "airline": "Air France"
    },
    {
      "date": "2025-07-09",
      "price": 10570,
      "airline": "Air France"
    },
    {
      "date": "2025-07-10",
      "price": 10770,
      "airline": "Japan Airlines"
    },
    {
      "date": "2025-07-11",
      "price": 12980,
      "airline": "ANA"
    },
    {
      "date": "2025-07-12",
      "price": 11960,
      "airline": "Various"
    },
    {
      "date": "2025-07-13",
      "price": 11410,
      "airline": "Japan Airlines"
    },
    {
      "date": "2025-07-14",
      "price": 10690,
      "airline": "ANA"
    },
    {
      "date": "2025-07-15",
      "price": 10020,
      "airline": "ANA"
    },
    {
      "date": "2025-07-16",
      "price": 10440,
      "airline": "Air France"
    },
    {
      "date": "2025-07-17",
      "price": 8830,
      "airline": "Japan Airlines"
    },
    {
      "date": "2025-07-18",
      "price": 13240,
      "airline": "Air France"
    },
    {
      "date": "2025-07-19",
      "price": 11340,
      "airline": "Various"
    },
    {
      "date": "2025-07-20",
      "price": 12100,
      "airline": "Japan Airlines"
    },
    {
      "date": "2025-07-21",
      "price": 10610,
      "airline": "Air France"
    },
    {
      "date": "2025-07-22",
      "price": 10110,
      "airline": "ANA"
    },
    {
      "date": "2025-07-23",
      "price": 10010,
      "airline": "Air France"
    },
    {
      "date": "2025-07-24",
      "price": 10750,
      "airline": "Various"
    },
    {
      "date": "2025-07-25",
      "price": 10950,
      "airline": "Japan Airlines"
    },
    {
      "date": "2025-07-26",
      "price": 12130,
      "airline": "ANA"
    },
    {
      "date": "2025-07-27",
      "price": 11450,
      "airline": "Japan Airlines"
    },
    {
      "date": "2025-07-28",
      "price": 10700,
      "airline": "Various"
    },
    {
      "date": "2025-07-29",
      "price": 11020,
      "airline": "ANA"
    },
    {
      "date": "2025-07-30",
      "price": 10750,
      "airline": "Air France"
    },
    {
      "date": "2025-07-31",
      "price": 9610,
      "airline": "Japan Airlines"
    },
    {
      "date": "2025-08-01",
      "price": 9560,
      "airline": "Air France"
    },
    {
      "date": "2025-08-02",
      "price": 11140,
      "airline": "Air France"
    },
    {
      "date": "2025-08-03",
      "price": 11480,
      "airline": "Japan Airlines"
    },
    {
      "date": "2025-08-04",
      "price": 11410,
      "airline": "ANA"
    },
    {
      "date": "2025-08-05",
      "price": 11160,
      "airline": "ANA"
    },
    {
      "date": "2025-08-06",
      "price": 10440,
      "airline": "Japan Airlines"
    },
    {
      "date": "2025-08-07",
      "price": 10310,
      "airline": "Air France"
    },
    {
      "date": "2025-08-08",
      "price": 10710,
      "airline": "Various"
    },
    {
      "date": "2025-08-09",
      "price": 11510,
      "airline": "Various"
    },
    {
      "date": "2025-08-10",
      "price": 11690,
      "airline": "Japan Airlines"
    },
    {
      "date": "2025-08-11",
      "price": 9840,
      "airline": "ANA"
    },
    {
      "date": "2025-08-12",
      "price": 10790,
      "airline": "ANA"
    },
    {
      "date": "2025-08-13",
      "price": 8910,
      "airline": "Japan Airlines"
    },
    {
      "date": "2025-08-14",
      "price": 11330,
      "airline": "Japan Airlines"
    },
    {
      "date": "2025-08-15",
      "price": 10410,
      "airline": "Japan Airlines"
    },
    {
      "date": "2025-08-16",
      "price": 11930,
      "airline": "ANA"
    },
    {
      "date": "2025-08-17",
      "price": 11040,
      "airline": "Air France"
    },
    {
      "date": "2025-08-18",
      "price": 10420,
      "airline": "Air France"
    },
    {
      "date": "2025-08-19",
      "price": 10170,
      "airline": "Various"
    },
    {
      "date": "2025-08-20",
      "price": 10680,
      "airline": "ANA"
    },
    {
      "date": "2025-08-21",
      "price": 12260,
      "airline": "Air France"
    },
    {
      "date": "2025-08-22",
      "price": 11900,
      "airline": "Japan Airlines"
    },
    {
      "date": "2025-08-23",
      "price": 8920,
      "airline": "Various"
    },
    {
      "date": "2025-08-24",
      "price": 12410,
      "airline": "Various"
    },
    {
      "date": "2025-08-25",
      "price": 10290,
      "airline": "ANA"
    },
    {
      "date": "2025-08-26",
      "price": 10810,
      "airline": "Air France"
    },
    {
      "date": "2025-08-27",
      "price": 10780,
      "airline": "Air France"
    },
    {
      "date": "2025-08-28",
      "price": 11100,
      "airline": "Japan Airlines"
    },
    {
      "date": "2025-08-29",
      "price": 9880,
      "airline": "Various"
    },
    {
      "date": "2025-08-30",
      "price": 10330,
      "airline": "ANA"
    },
    {
      "date": "2025-08-31",
      "price": 11840,
      "airline": "Air France"
    },
    {
      "date": "2025-09-01",
      "price": 12050,
      "airline": "Various"
    },
    {
      "date": "2025-09-02",
      "price": 12010,
      "airline": "Japan Airlines"
    },
    {
      "date": "2025-09-03",
      "price": 10460,
      "airline": "Air France"
    },
    {
      "date": "2025-09-04",
      "price": 10590,
      "airline": "ANA"
    },
    {
      "date": "2025-09-05",
      "price": 11370,
      "airline": "Air France"
    },
    {
      "date": "2025-09-06",
      "price": 11140,
      "airline": "Japan Airlines"
    },
    {
      "date": "2025-09-07",
      "price": 10550,
      "airline": "Air France"
    },
    {
      "date": "2025-09-08",
      "price": 10340,
      "airline": "Various"
    },
    {
      "date": "2025-09-09",
      "price": 10770,
      "airline": "ANA"
    },
    {
      "date": "2025-09-10",
      "price": 11060,
      "airline": "Japan Airlines"
    },
    {
      "date": "2025-09-11",
      "price": 11130,
      "airline": "Air France"
    },
    {
      "date": "2025-09-12",
      "price": 10660,
      "airline": "Air France"
    },
    {
      "date": "2025-09-13",
      "price": 10300,
      "airline": "ANA"
    },
    {
      "date": "2025-09-14",
      "price": 11280,
      "airline": "Air France"
    },
    {
      "date": "2025-09-15",
      "price": 10330,
      "airline": "Various"
    },
    {
      "date": "2025-09-16",
      "price": 10590,
      "airline": "Air France"
    },
    {
      "date": "2025-09-17",
      "price": 10170,
      "airline": "Japan Airlines"
    },
    {
      "date": "2025-09-18",
      "price": 10800,
      "airline": "ANA"
    },
    {
      "date": "2025-09-19",
      "price": 11830,
      "airline": "Air France"
    },
    {
      "date": "2025-09-20",
      "price": 11270,
      "airline": "Air France"
    },
    {
      "date": "2025-09-21",
      "price": 10960,
      "airline": "Air France"
    },
    {
      "date": "2025-09-22",
      "price": 10220,
      "airline": "Air France"
    },
    {
      "date": "2025-09-23",
      "price": 12040,
      "airline": "Japan Airlines"
    },
    {
      "date": "2025-09-24",
      "price": 10240,
      "airline": "ANA"
    },
    {
      "date": "2025-09-25",
      "price": 10510,
      "airline": "Japan Airlines"
    },
    {
      "date": "2025-09-26",
      "price": 11210,
      "airline": "ANA"
    },
    {
      "date": "2025-09-27",
      "price": 12190,
      "airline": "Air France"
    },
    {
      "date": "2025-09-28",
      "price": 12510,
      "airline": "Air France"
    },
    {
      "date": "2025-09-29",
      "price": 10690,
      "airline": "Air France"
    },
    {
      "date": "2025-09-30",
      "price": 11390,
      "airline": "ANA"
    },
    {
      "date": "2025-10-01",
      "price": 11560,
      "airline": "Air France"
    },
    {
      "date": "2025-10-02",
      "price": 10700,
      "airline": "Various"
    },
    {
      "date": "2025-10-03",
      "price": 13400,
      "airline": "Various"
    },
    {
      "date": "2025-10-04",
      "price": 11600,
      "airline": "Japan Airlines"
    },
    {
      "date": "2025-10-05",
      "price": 11260,
      "airline": "ANA"
    },
    {
      "date": "2025-10-06",
      "price": 10260,
      "airline": "Japan Airlines"
    },
    {
      "date": "2025-10-07",
      "price": 11410,
      "airline": "ANA"
    },
    {
      "date": "2025-10-08",
      "price": 10710,
      "airline": "Japan Airlines"
    },
    {
      "date": "2025-10-09",
      "price": 11150,
      "airline": "Various"
    },
    {
      "date": "2025-10-10",
      "price": 12630,
      "airline": "Various"
    },
    {
      "date": "2025-10-11",
      "price": 12940,
      "airline": "Air France"
    },
    {
      "date": "2025-10-12",
      "price": 11980,
      "airline": "Japan Airlines"
    },
    {
      "date": "2025-10-13",
      "price": 10340,
      "airline": "Various"
    },
    {
      "date": "2025-10-14",
      "price": 8710,
      "airline": "ANA"
    },
    {
      "date": "2025-10-15",
      "price": 10530,
      "airline": "Air France"
    },
    {
      "date": "2025-10-16",
      "price": 11070,
      "airline": "Air France"
    },
    {
      "date": "2025-10-17",
      "price": 12940,
      "airline": "Japan Airlines"
    },
    {
      "date": "2025-10-18",
      "price": 11140,
      "airline": "ANA"
    },
    {
      "date": "2025-10-19",
      "price": 11390,
      "airline": "Various"
    },
    {
      "date": "2025-10-20",
      "price": 10780,
      "airline": "Various"
    },
    {
      "date": "2025-10-21",
      "price": 10190,
      "airline": "ANA"
    },
    {
      "date": "2025-10-22",
      "price": 10790,
      "airline": "Air France"
    },
    {
      "date": "2025-10-23",
      "price": 11070,
      "airline": "Air France"
    },
    {
      "date": "2025-10-24",
      "price": 10940,
      "airline": "Various"
    },
    {
      "date": "2025-10-25",
      "price": 12070,
      "airline": "ANA"
    },
    {
      "date": "2025-10-26",
      "price": 11930,
      "airline": "Air France"
    },
    {
      "date": "2025-10-27",
      "price": 9730,
      "airline": "Air France"
    },
    {
      "date": "2025-10-28",
      "price": 10000,
      "airline": "ANA"
    },
    {
      "date": "2025-10-29",
      "price": 10490,
      "airline": "Various"
    },
    {
      "date": "2025-10-30",
      "price": 10510,
      "airline": "Air France"
    },
    {
      "date": "2025-10-31",
      "price": 11140,
      "airline": "Japan Airlines"
    },
    {
      "date": "2025-11-01",
      "price": 12730,
      "airline": "Japan Airlines"
    },
    {
      "date": "2025-11-02",
      "price": 12870,
      "airline": "Air France"
    },
    {
      "date": "2025-11-03",
      "price": 12680,
      "airline": "ANA"
    },
    {
      "date": "2025-11-04",
      "price": 12260,
      "airline": "Various"
    },
    {
      "date": "2025-11-05",
      "price": 11410,
      "airline": "Japan Airlines"
    },
    {
      "date": "2025-11-06",
      "price": 11950,
      "airline": "Air France"
    },
    {
      "date": "2025-11-07",
      "price": 14020,
      "airline": "Various"
    },
    {
      "date": "2025-11-08",
      "price": 13430,
      "airline": "Air France"
    },
    {
      "date": "2025-11-09",
      "price": 13130,
      "airline": "Air France"
    },
    {
      "date": "2025-11-10",
      "price": 12300,
      "airline": "Japan Airlines"
    },
    {
      "date": "2025-11-11",
      "price": 11290,
      "airline": "ANA"
    },
    {
      "date": "2025-11-12",
      "price": 11600,
      "airline": "Air France"
    },
    {
      "date": "2025-11-13",
      "price": 11050,
      "airline": "Air France"
    },
    {
      "date": "2025-11-14",
      "price": 13020,
      "airline": "ANA"
    },
    {
      "date": "2025-11-15",
      "price": 12180,
      "airline": "Air France"
    },
    {
      "date": "2025-11-16",
      "price": 13160,
      "airline": "Air France"
    },
    {
      "date": "2025-11-17",
      "price": 12980,
      "airline": "ANA"
    },
    {
      "date": "2025-11-18",
      "price": 10610,
      "airline": "Various"
    },
    {
      "date": "2025-11-19",
      "price": 11300,
      "airline": "Various"
    },
    {
      "date": "2025-11-20",
      "price": 10620,
      "airline": "Various"
    },
    {
      "date": "2025-11-21",
      "price": 13170,
      "airline": "Japan Airlines"
    },
    {
      "date": "2025-11-22",
      "price": 13840,
      "airline": "ANA"
    },
    {
      "date": "2025-11-23",
      "price": 12600,
      "airline": "Air France"
    },
    {
      "date": "2025-11-24",
      "price": 12440,
      "airline": "Air France"
    },
    {
      "date": "2025-11-25",
      "price": 12330,
      "airline": "ANA"
    },
    {
      "date": "2025-11-26",
      "price": 12080,
      "airline": "Japan Airlines"
    },
    {
      "date": "2025-11-27",
      "price": 12130,
      "airline": "Various"
    },
    {
      "date": "2025-11-28",
      "price": 14300,
      "airline": "Air France"
    },
    {
      "date": "2025-11-29",
      "price": 14070,
      "airline": "Japan Airlines"
    },
    {
      "date": "2025-11-30",
      "price": 13200,
      "airline": "Air France"
    },
    {
      "date": "2025-12-01",
      "price": 10210,
      "airline": "Japan Airlines"
    },
    {
      "date": "2025-12-02",
      "price": 12090,
      "airline": "Various"
    },
    {
      "date": "2025-12-03",
      "price": 11820,
      "airline": "Air France"
    },
    {
      "date": "2025-12-04",
      "price": 13460,
      "airline": "ANA"
    },
    {
      "date": "2025-12-05",
      "price": 12430,
      "airline": "Japan Airlines"
    },
    {
      "date": "2025-12-06",
      "price": 13750,
      "airline": "Various"
    },
    {
      "date": "2025-12-07",
      "price": 12190,
      "airline": "Air France"
    },
    {
      "date": "2025-12-08",
      "price": 11990,
      "airline": "Japan Airlines"
    },
    {
      "date": "2025-12-09",
      "price": 12490,
      "airline": "ANA"
    },
    {
      "date": "2025-12-10",
      "price": 11310,
      "airline": "Various"
    },
    {
      "date": "2025-12-11",
      "price": 10840,
      "airline": "ANA"
    },
    {
      "date": "2025-12-12",
      "price": 13110,
      "airline": "Various"
    },
    {
      "date": "2025-12-13",
      "price": 11700,
      "airline": "Japan Airlines"
    },
    {
      "date": "2025-12-14",
      "price": 11570,
      "airline": "Japan Airlines"
    },
    {
      "date": "2025-12-15",
      "price": 11690,
      "airline": "ANA"
    },
    {
      "date": "2025-12-16",
      "price": 14090,
      "airline": "Various"
    },
    {
      "date": "2025-12-17",
      "price": 12200,
      "airline": "Japan Airlines"
    },
    {
      "date": "2025-12-18",
      "price": 12280,
      "airline": "ANA"
    },
    {
      "date": "2025-12-19",
      "price": 13400,
      "airline": "Japan Airlines"
    },
    {
      "date": "2025-12-20",
      "price": 13480,
      "airline": "Various"
    },
    {
      "date": "2025-12-21",
      "price": 12330,
      "airline": "Japan Airlines"
    },
    {
      "date": "2025-12-22",
      "price": 11490,
      "airline": "Various"
    },
    {
      "date": "2025-12-23",
      "price": 12640,
      "airline": "Various"
    },
    {
      "date": "2025-12-24",
      "price": 12410,
      "airline": "Japan Airlines"
    },
    {
      "date": "2025-12-25",
      "price": 10560,
      "airline": "Air France"
    },
    {
      "date": "2025-12-26",
      "price": 12730,
      "airline": "Japan Airlines"
    },
    {
      "date": "2025-12-27",
      "price": 11990,
      "airline": "Various"
    },
    {
      "date": "2025-12-28",
      "price": 13080,
      "airline": "Various"
    },
    {
      "date": "2025-12-29",
      "price": 12370,
      "airline": "Various"
    },
    {
      "date": "2025-12-30",
      "price": 11280,
      "airline": "Air France"
    },
    {
      "date": "2025-12-31",
      "price": 11630,
      "airline": "Air France"
    },
    {
      "date": "2026-01-01",
      "price": 11210,
      "airline": "Air France"
    },
    {
      "date": "2026-01-02",
      "price": 12560,
      "airline": "Japan Airlines"
    },
    {
      "date": "2026-01-03",
      "price": 11380,
      "airline": "Japan Airlines"
    },
    {
      "date": "2026-01-04",
      "price": 10700,
      "airline": "ANA"
    },
    {
      "date": "2026-01-05",
      "price": 11370,
      "airline": "Various"
    },
    {
      "date": "2026-01-06",
      "price": 10350,
      "airline": "ANA"
    },
    {
      "date": "2026-01-07",
      "price": 10980,
      "airline": "Various"
    },
    {
      "date": "2026-01-08",
      "price": 9310,
      "airline": "ANA"
    },
    {
      "date": "2026-01-09",
      "price": 11200,
      "airline": "Air France"
    },
    {
      "date": "2026-01-10",
      "price": 11760,
      "airline": "ANA"
    },
    {
      "date": "2026-01-11",
      "price": 11520,
      "airline": "Air France"
    },
    {
      "date": "2026-01-12",
      "price": 10780,
      "airline": "Various"
    },
    {
      "date": "2026-01-13",
      "price": 10180,
      "airline": "Japan Airlines"
    },
    {
      "date": "2026-01-14",
      "price": 9290,
      "airline": "Air France"
    },
    {
      "date": "2026-01-15",
      "price": 10820,
      "airline": "Air France"
    },
    {
      "date": "2026-01-16",
      "price": 12040,
      "airline": "Japan Airlines"
    },
    {
      "date": "2026-01-17",
      "price": 11240,
      "airline": "Japan Airlines"
    },
    {
      "date": "2026-01-18",
      "price": 12580,
      "airline": "Air France"
    },
    {
      "date": "2026-01-19",
      "price": 10890,
      "airline": "Various"
    },
    {
      "date": "2026-01-20",
      "price": 11190,
      "airline": "Various"
    },
    {
      "date": "2026-01-21",
      "price": 10970,
      "airline": "Air France"
    },
    {
      "date": "2026-01-22",
      "price": 10190,
      "airline": "ANA"
    },
    {
      "date": "2026-01-23",
      "price": 11530,
      "airline": "Japan Airlines"
    },
    {
      "date": "2026-01-24",
      "price": 11950,
      "airline": "ANA"
    },
    {
      "date": "2026-01-25",
      "price": 12710,
      "airline": "Various"
    },
    {
      "date": "2026-01-26",
      "price": 10450,
      "airline": "Various"
    },
    {
      "date": "2026-01-27",
      "price": 11370,
      "airline": "Various"
    },
    {
      "date": "2026-01-28",
      "price": 10060,
      "airline": "Air France"
    },
    {
      "date": "2026-01-29",
      "price": 11020,
      "airline": "Japan Airlines"
    },
    {
      "date": "2026-01-30",
      "price": 11940,
      "airline": "Air France"
    },
    {
      "date": "2026-01-31",
      "price": 10850,
      "airline": "ANA"
    },
    {
      "date": "2026-02-01",
      "price": 12480,
      "airline": "Air France"
    },
    {
      "date": "2026-02-02",
      "price": 9400,
      "airline": "ANA"
    },
    {
      "date": "2026-02-03",
      "price": 10880,
      "airline": "Japan Airlines"
    },
    {
      "date": "2026-02-04",
      "price": 9160,
      "airline": "Air France"
    },
    {
      "date": "2026-02-05",
      "price": 9260,
      "airline": "ANA"
    },
    {
      "date": "2026-02-06",
      "price": 11850,
      "airline": "Various"
    },
    {
      "date": "2026-02-07",
      "price": 10630,
      "airline": "Japan Airlines"
    },
    {
      "date": "2026-02-08",
      "price": 12020,
      "airline": "Air France"
    },
    {
      "date": "2026-02-09",
      "price": 10360,
      "airline": "Japan Airlines"
    },
    {
      "date": "2026-02-10",
      "price": 10350,
      "airline": "Japan Airlines"
    },
    {
      "date": "2026-02-11",
      "price": 11160,
      "airline": "Japan Airlines"
    },
    {
      "date": "2026-02-12",
      "price": 9830,
      "airline": "Various"
    },
    {
      "date": "2026-02-13",
      "price": 12270,
      "airline": "Japan Airlines"
    },
    {
      "date": "2026-02-14",
      "price": 12500,
      "airline": "Various"
    },
    {
      "date": "2026-02-15",
      "price": 13280,
      "airline": "Various"
    },
    {
      "date": "2026-02-16",
      "price": 11680,
      "airline": "Various"
    },
    {
      "date": "2026-02-17",
      "price": 10950,
      "airline": "ANA"
    },
    {
      "date": "2026-02-18",
      "price": 10930,
      "airline": "ANA"
    },
    {
      "date": "2026-02-19",
      "price": 8980,
      "airline": "Various"
    },
    {
      "date": "2026-02-20",
      "price": 11380,
      "airline": "ANA"
    },
    {
      "date": "2026-02-21",
      "price": 11580,
      "airline": "Japan Airlines"
    },
    {
      "date": "2026-02-22",
      "price": 11920,
      "airline": "Various"
    },
    {
      "date": "2026-02-23",
      "price": 10820,
      "airline": "Various"
    },
    {
      "date": "2026-02-24",
      "price": 10530,
      "airline": "ANA"
    },
    {
      "date": "2026-02-25",
      "price": 10100,
      "airline": "ANA"
    },
    {
      "date": "2026-02-26",
      "price": 10160,
      "airline": "Air France"
    },
    {
      "date": "2026-02-27",
      "price": 12290,
      "airline": "ANA"
    },
    {
      "date": "2026-02-28",
      "price": 12370,
      "airline": "Japan Airlines"
    },
    {
      "date": "2026-03-01",
      "price": 17530,
      "airline": "Various"
    },
    {
      "date": "2026-03-02",
      "price": 13920,
      "airline": "Air France"
    },
    {
      "date": "2026-03-03",
      "price": 13170,
      "airline": "Air France"
    },
    {
      "date": "2026-03-04",
      "price": 13770,
      "airline": "ANA"
    },
    {
      "date": "2026-03-05",
      "price": 12960,
      "airline": "Air France"
    },
    {
      "date": "2026-03-06",
      "price": 15650,
      "airline": "Air France"
    },
    {
      "date": "2026-03-07",
      "price": 14130,
      "airline": "Japan Airlines"
    },
    {
      "date": "2026-03-08",
      "price": 12490,
      "airline": "ANA"
    },
    {
      "date": "2026-03-09",
      "price": 13800,
      "airline": "Air France"
    },
    {
      "date": "2026-03-10",
      "price": 13980,
      "airline": "Various"
    },
    {
      "date": "2026-03-11",
      "price": 15970,
      "airline": "Air France"
    },
    {
      "date": "2026-03-12",
      "price": 14560,
      "airline": "Japan Airlines"
    },
    {
      "date": "2026-03-13",
      "price": 15790,
      "airline": "Japan Airlines"
    },
    {
      "date": "2026-03-14",
      "price": 15430,
      "airline": "Air France"
    },
    {
      "date": "2026-03-15",
      "price": 13460,
      "airline": "Air France"
    },
    {
      "date": "2026-03-16",
      "price": 13550,
      "airline": "Japan Airlines"
    },
    {
      "date": "2026-03-17",
      "price": 12680,
      "airline": "Air France"
    },
    {
      "date": "2026-03-18",
      "price": 13390,
      "airline": "Various"
    },
    {
      "date": "2026-03-19",
      "price": 13510,
      "airline": "Japan Airlines"
    },
    {
      "date": "2026-03-20",
      "price": 14300,
      "airline": "Various"
    },
    {
      "date": "2026-03-21",
      "price": 17560,
      "airline": "Various"
    },
    {
      "date": "2026-03-22",
      "price": 15900,
      "airline": "Japan Airlines"
    },
    {
      "date": "2026-03-23",
      "price": 13300,
      "airline": "Air France"
    },
    {
      "date": "2026-03-24",
      "price": 14280,
      "airline": "Japan Airlines"
    },
    {
      "date": "2026-03-25",
      "price": 13120,
      "airline": "Japan Airlines"
    },
    {
      "date": "2026-03-26",
      "price": 12280,
      "airline": "Various"
    },
    {
      "date": "2026-03-27",
      "price": 15290,
      "airline": "ANA"
    },
    {
      "date": "2026-03-28",
      "price": 16380,
      "airline": "Various"
    },
    {
      "date": "2026-03-29",
      "price": 16240,
      "airline": "Various"
    },
    {
      "date": "2026-03-30",
      "price": 12660,
      "airline": "Various"
    },
    {
      "date": "2026-03-31",
      "price": 14240,
      "airline": "Japan Airlines"
    },
    {
      "date": "2026-04-01",
      "price": 12650,
      "airline": "ANA"
    },
    {
      "date": "2026-04-02",
      "price": 12650,
      "airline": "Japan Airlines"
    },
    {
      "date": "2026-04-03",
      "price": 15290,
      "airline": "ANA"
    },
    {
      "date": "2026-04-04",
      "price": 16900,
      "airline": "ANA"
    },
    {
      "date": "2026-04-05",
      "price": 17850,
      "airline": "Japan Airlines"
    },
    {
      "date": "2026-04-06",
      "price": 13040,
      "airline": "Air France"
    },
    {
      "date": "2026-04-07",
      "price": 14440,
      "airline": "Air France"
    },
    {
      "date": "2026-04-08",
      "price": 15670,
      "airline": "Air France"
    },
    {
      "date": "2026-04-09",
      "price": 13130,
      "airline": "Various"
    },
    {
      "date": "2026-04-10",
      "price": 16100,
      "airline": "Air France"
    },
    {
      "date": "2026-04-11",
      "price": 15850,
      "airline": "ANA"
    },
    {
      "date": "2026-04-12",
      "price": 14580,
      "airline": "Various"
    },
    {
      "date": "2026-04-13",
      "price": 14480,
      "airline": "Japan Airlines"
    },
    {
      "date": "2026-04-14",
      "price": 15800,
      "airline": "ANA"
    },
    {
      "date": "2026-04-15",
      "price": 14490,
      "airline": "Japan Airlines"
    },
    {
      "date": "2026-04-16",
      "price": 14810,
      "airline": "Japan Airlines"
    },
    {
      "date": "2026-04-17",
      "price": 15570,
      "airline": "Japan Airlines"
    },
    {
      "date": "2026-04-18",
      "price": 13610,
      "airline": "Air France"
    },
    {
      "date": "2026-04-19",
      "price": 17010,
      "airline": "Air France"
    },
    {
      "date": "2026-04-20",
      "price": 12830,
      "airline": "Air France"
    },
    {
      "date": "2026-04-21",
      "price": 13510,
      "airline": "Various"
    },
    {
      "date": "2026-04-22",
      "price": 13670,
      "airline": "ANA"
    },
    {
      "date": "2026-04-23",
      "price": 14410,
      "airline": "ANA"
    },
    {
      "date": "2026-04-24",
      "price": 14060,
      "airline": "Japan Airlines"
    },
    {
      "date": "2026-04-25",
      "price": 15010,
      "airline": "Japan Airlines"
    },
    {
      "date": "2026-04-26",
      "price": 16780,
      "airline": "ANA"
    },
    {
      "date": "2026-04-27",
      "price": 13250,
      "airline": "Air France"
    },
    {
      "date": "2026-04-28",
      "price": 13560,
      "airline": "Various"
    },
    {
      "date": "2026-04-29",
      "price": 13800,
      "airline": "Various"
    },
    {
      "date": "2026-04-30",
      "price": 14050,
      "airline": "Japan Airlines"
    },
    {
      "date": "2026-05-01",
      "price": 11190,
      "airline": "ANA"
    },
    {
      "date": "2026-05-02",
      "price": 9910,
      "airline": "Japan Airlines"
    },
    {
      "date": "2026-05-03",
      "price": 11860,
      "airline": "Various"
    },
    {
      "date": "2026-05-04",
      "price": 10780,
      "airline": "Japan Airlines"
    },
    {
      "date": "2026-05-05",
      "price": 9180,
      "airline": "Air France"
    },
    {
      "date": "2026-05-06",
      "price": 11710,
      "airline": "Japan Airlines"
    },
    {
      "date": "2026-05-07",
      "price": 10760,
      "airline": "Japan Airlines"
    },
    {
      "date": "2026-05-08",
      "price": 12530,
      "airline": "ANA"
    },
    {
      "date": "2026-05-09",
      "price": 11460,
      "airline": "Various"
    },
    {
      "date": "2026-05-10",
      "price": 10750,
      "airline": "Various"
    },
    {
      "date": "2026-05-11",
      "price": 11850,
      "airline": "Japan Airlines"
    },
    {
      "date": "2026-05-12",
      "price": 9870,
      "airline": "Various"
    },
    {
      "date": "2026-05-13",
      "price": 8610,
      "airline": "ANA"
    },
    {
      "date": "2026-05-14",
      "price": 11080,
      "airline": "Air France"
    },
    {
      "date": "2026-05-15",
      "price": 10620,
      "airline": "Various"
    },
    {
      "date": "2026-05-16",
      "price": 10240,
      "airline": "ANA"
    },
    {
      "date": "2026-05-17",
      "price": 10990,
      "airline": "Air France"
    },
    {
      "date": "2026-05-18",
      "price": 10840,
      "airline": "Air France"
    },
    {
      "date": "2026-05-19",
      "price": 9330,
      "airline": "Various"
    },
    {
      "date": "2026-05-20",
      "price": 10150,
      "airline": "ANA"
    },
    {
      "date": "2026-05-21",
      "price": 10250,
      "airline": "Various"
    },
    {
      "date": "2026-05-22",
      "price": 11460,
      "airline": "Various"
    },
    {
      "date": "2026-05-23",
      "price": 10060,
      "airline": "Air France"
    },
    {
      "date": "2026-05-24",
      "price": 11790,
      "airline": "Japan Airlines"
    },
    {
      "date": "2026-05-25",
      "price": 9870,
      "airline": "Air France"
    },
    {
      "date": "2026-05-26",
      "price": 11130,
      "airline": "Various"
    },
    {
      "date": "2026-05-27",
      "price": 11290,
      "airline": "Air France"
    },
    {
      "date": "2026-05-28",
      "price": 9890,
      "airline": "ANA"
    },
    {
      "date": "2026-05-29",
      "price": 11110,
      "airline": "ANA"
    },
    {
      "date": "2026-05-30",
      "price": 13750,
      "airline": "ANA"
    },
    {
      "date": "2026-05-31",
      "price": 10600,
      "airline": "Various"
    },
    {
      "date": "2026-06-01",
      "price": 10880,
      "airline": "Japan Airlines"
    },
    {
      "date": "2026-06-02",
      "price": 12440,
      "airline": "Japan Airlines"
    },
    {
      "date": "2026-06-03",
      "price": 10920,
      "airline": "ANA"
    },
    {
      "date": "2026-06-04",
      "price": 10570,
      "airline": "ANA"
    },
    {
      "date": "2026-06-05",
      "price": 10560,
      "airline": "Air France"
    },
    {
      "date": "2026-06-06",
      "price": 11500,
      "airline": "Air France"
    },
    {
      "date": "2026-06-07",
      "price": 12150,
      "airline": "Air France"
    },
    {
      "date": "2026-06-08",
      "price": 11180,
      "airline": "ANA"
    },
    {
      "date": "2026-06-09",
      "price": 12210,
      "airline": "ANA"
    },
    {
      "date": "2026-06-10",
      "price": 7750,
      "airline": "Various"
    },
    {
      "date": "2026-06-11",
      "price": 10150,
      "airline": "Various"
    },
    {
      "date": "2026-06-12",
      "price": 12210,
      "airline": "ANA"
    },
    {
      "date": "2026-06-13",
      "price": 11570,
      "airline": "Various"
    },
    {
      "date": "2026-06-14",
      "price": 10320,
      "airline": "Japan Airlines"
    },
    {
      "date": "2026-06-15",
      "price": 9990,
      "airline": "Various"
    },
    {
      "date": "2026-06-16",
      "price": 9850,
      "airline": "ANA"
    },
    {
      "date": "2026-06-17",
      "price": 10540,
      "airline": "Japan Airlines"
    },
    {
      "date": "2026-06-18",
      "price": 10910,
      "airline": "Japan Airlines"
    },
    {
      "date": "2026-06-19",
      "price": 12880,
      "airline": "Air France"
    },
    {
      "date": "2026-06-20",
      "price": 11740,
      "airline": "Japan Airlines"
    },
    {
      "date": "2026-06-21",
      "price": 12190,
      "airline": "ANA"
    },
    {
      "date": "2026-06-22",
      "price": 10880,
      "airline": "Japan Airlines"
    },
    {
      "date": "2026-06-23",
      "price": 10170,
      "airline": "Air France"
    },
    {
      "date": "2026-06-24",
      "price": 9750,
      "airline": "ANA"
    },
    {
      "date": "2026-06-25",
      "price": 10210,
      "airline": "ANA"
    },
    {
      "date": "2026-06-26",
      "price": 10820,
      "airline": "ANA"
    },
    {
      "date": "2026-06-27",
      "price": 12370,
      "airline": "Air France"
    },
    {
      "date": "2026-06-28",
      "price": 11910,
      "airline": "Japan Airlines"
    },
    {
      "date": "2026-06-29",
      "price": 10350,
      "airline": "Japan Airlines"
    },
    {
      "date": "2026-06-30",
      "price": 10750,
      "airline": "ANA"
    },
    {
      "date": "2026-07-01",
      "price": 10600,
      "airline": "ANA"
    },
    {
      "date": "2026-07-02",
      "price": 10170,
      "airline": "Japan Airlines"
    },
    {
      "date": "2026-07-03",
      "price": 11540,
      "airline": "Japan Airlines"
    },
    {
      "date": "2026-07-04",
      "price": 11100,
      "airline": "Japan Airlines"
    },
    {
      "date": "2026-07-05",
      "price": 11850,
      "airline": "Various"
    }
  ]
}